tc_tui/__init__.py
tc_tui/capture_io.py
tc_tui/config.py
tc_tui/coverage.py
tc_tui/dependency_checker.py
tc_tui/file_helper.py
tc_tui/io_capturer.py
tc_tui/main.py
tc_tui/toml/__init__.py
tc_tui/toml/project_definition.py
tc_tui/toml/testcase.py
tc_tui/toml/toml_handler.py
tc_tui/ui/__init__.py
tc_tui/ui/menu_handler.py
tc_tui-0.1.0.dist-info/licenses/LICENSE
tc_tui-0.1.0.dist-info/METADATA
tc_tui-0.1.0.dist-info/WHEEL
tc_tui-0.1.0.dist-info/entry_points.txt
tc_tui-0.1.0.dist-info/top_level.txt
tc_tui-0.1.0.dist-info/RECORD
