Metadata-Version: 2.4
Name: tc-tui
Version: 0.1.0
Summary: A TUI for creating testcases for the ISP/OOP1 courses at TU Graz
Author-email: Kilian Kier <kierkilian@gmail.com>
License-Expression: MIT
Requires-Python: >=3.6
License-File: LICENSE
Requires-Dist: prompt_toolkit
Requires-Dist: toml
Dynamic: license-file
